[
  {
    "id": "6281235144606@s.whatsapp.net",
    "limit": 4
  },
  {
    "id": "6287784362530@s.whatsapp.net",
    "limit": 1
  },
  {
    "id": "6285162672174@s.whatsapp.net",
    "limit": 0
  },
  {
    "id": "6283189181791@s.whatsapp.net",
    "limit": 13
  },
  {
    "id": "6283175467100@s.whatsapp.net",
    "limit": 2
  },
  {
    "id": "6288287383676@s.whatsapp.net",
    "limit": 1
  },
  {
    "id": "6285268762988@s.whatsapp.net",
    "limit": 4
  },
  {
    "id": "6282351248496@s.whatsapp.net",
    "limit": 3
  },
  {
    "id": "6281355509218@s.whatsapp.net",
    "limit": 1
  },
  {
    "id": "6283175220590@s.whatsapp.net",
    "limit": 1
  },
  {
    "id": "6285832801268@s.whatsapp.net",
    "limit": 0
  },
  {
    "id": "6281261634095@s.whatsapp.net",
    "limit": 6
  },
  {
    "id": "62895612472060@s.whatsapp.net",
    "limit": 0
  },
  {
    "id": "6289504865561@s.whatsapp.net",
    "limit": 0
  },
  {
    "id": "6281330759460@s.whatsapp.net",
    "limit": 0
  },
  {
    "id": "6285719417015@s.whatsapp.net",
    "limit": 2
  },
  {
    "id": "62895402219642@s.whatsapp.net",
    "limit": 4
  },
  {
    "id": "6282145093388@s.whatsapp.net",
    "limit": 3
  },
  {
    "id": "6285939191131@s.whatsapp.net",
    "limit": 2
  },
  {
    "id": "628816626924@s.whatsapp.net",
    "limit": 4
  },
  {
    "id": "6282141447886@s.whatsapp.net",
    "limit": 5
  }
]